{
  "lastCollectedAt": "2026-07-20T19:16:48.664Z",
  "lastRunStatus": "partial",
  "lastRunNewItems": 2,
  "totalItems": 2215,
  "collectors": {
    "naver": {
      "lastCollectedAt": "2026-07-20T19:16:48.664Z",
      "lastRunStatus": "success",
      "lastRunNewItems": 2,
      "totalItems": 1999
    },
    "official": {
      "lastCollectedAt": "2026-07-20T19:16:48.664Z",
      "lastRunStatus": "partial",
      "lastRunNewItems": 0,
      "totalItems": 1
    },
    "youtube": {
      "lastCollectedAt": "2026-07-20T14:35:06.459Z",
      "lastRunStatus": "success",
      "lastRunNewItems": 30,
      "totalItems": 215
    }
  }
}
