[
  {
    "id": "item_29a98815a2d782a1",
    "type": "news",
    "title": "'월드컵 스타' 황인범, 포르투갈 최고 명문 포르투가 부른다...신문 1면...",
    "summary": "이번 북중미 월드컵 참사는 단순히 경기력과 실력의 문제가 아닌, 대한축구협회 밀실 행정의 민낯을 보여줬다는 점에서 전 국민의 공분을 샀다. 결과는 처참했지만, 황인범의 활약만큼은 빛났다. 황인범은 체코와의...",
    "url": "https://www.fourfourtwo.co.kr/news/articleView.html?idxno=94704",
    "originalUrl": "https://www.fourfourtwo.co.kr/news/articleView.html?idxno=94704",
    "publisher": "fourfourtwo.co.kr",
    "publishedAt": "2026-07-12T04:55:00.000Z",
    "collectedAt": "2026-07-12T04:59:19.492Z",
    "matchedKeywords": [
      "대한축구협회",
      "축구협회"
    ],
    "issueTags": [],
    "personTags": [],
    "sourceType": "news",
    "isOfficial": false,
    "relevanceScore": 30,
    "relevanceTier": "secondary",
    "labels": []
  },
  {
    "id": "item_d74dd9fbad90914d",
    "type": "news",
    "title": "경찰, 홍명보·정몽규 수사 본격화…14일 고발인 조사",
    "summary": "정몽규 전 대한 축구협회 장과 이임생 전 기술이사가 홍명보 전 국가대표팀 감독 선임 과정에서 전력강화위원회를 협박했다며 추가 고발이 된 사건에 대해 경찰이 수사에 들어갑니다. 서울경찰청 광역수사단...",
    "url": "https://www.ichannela.com/news/main/news_detailPage.do?publishId=000000539253",
    "originalUrl": "https://www.ichannela.com/news/main/news_detailPage.do?publishId=000000539253",
    "publisher": "ichannela.com",
    "publishedAt": "2026-07-12T04:55:00.000Z",
    "collectedAt": "2026-07-12T04:59:19.492Z",
    "matchedKeywords": [
      "\"이임생\" 대한축구협회",
      "\"이임생\" 축구협회",
      "\"정몽규\" 대한축구협회",
      "\"정몽규\" 축구협회",
      "\"홍명보\" 대한축구협회",
      "\"홍명보\" 축구협회",
      "감독 선임",
      "대표팀 감독",
      "대표팀 감독 선임",
      "대한축구협회",
      "대한축구협회장",
      "이임생",
      "전력강화위원회",
      "정몽규",
      "축구협회",
      "축구협회 감독 선임",
      "축구협회장",
      "홍명보"
    ],
    "issueTags": [
      "coach-appointment",
      "election"
    ],
    "personTags": [
      "person_chung_mong_gyu",
      "person_hong_myung_bo",
      "person_lee_im_saeng"
    ],
    "sourceType": "news",
    "isOfficial": false,
    "relevanceScore": 100,
    "labels": [
      "인물 언급"
    ]
  },
  {
    "id": "item_f6b7b2fa5a378bee",
    "type": "news",
    "title": "[뉴스초점] 22일 대한축구협회 청문회…홍명보 “피하지 않겠다”",
    "summary": "문체부 감사 에서는 전력강화위원회 기능이 무력화됐고, 홍 전 감독 선임 과정에서도 권한 없는 인사가 후보... 참고인으로는 박지성 K-축구 혁신위 공동위원장 등 10명을 채택했습니다. 다만 핵심 인사들이 실제 출석할지는...",
    "url": "http://www.yonhapnewstv.co.kr/news/MYH202607121351173gD",
    "originalUrl": "http://www.yonhapnewstv.co.kr/news/MYH202607121351173gD",
    "publisher": "yonhapnewstv.co.kr",
    "publishedAt": "2026-07-12T04:52:00.000Z",
    "collectedAt": "2026-07-12T04:59:19.492Z",
    "matchedKeywords": [
      "\"박지성\" 감사",
      "\"박지성\" 대한축구협회",
      "\"박지성\" 선거",
      "\"박지성\" 축구협회",
      "\"정몽규\" 감사",
      "\"정몽규\" 대한축구협회",
      "\"정몽규\" 선거",
      "\"정몽규\" 축구협회",
      "\"홍명보\" 감사",
      "\"홍명보\" 대한축구협회",
      "\"홍명보\" 선거",
      "\"홍명보\" 축구협회",
      "감독 선임",
      "감독 후보",
      "감사",
      "대표팀 감독",
      "대표팀 감독 선임",
      "대한축구협회",
      "대한축구협회장",
      "문체부 감사",
      "박지성",
      "전력강화위원회",
      "정몽규",
      "축구 혁신",
      "축구혁신위",
      "축구협회",
      "축구협회 감독 선임",
      "축구협회 감독 후보",
      "축구협회 감사",
      "축구협회 문체부 감사",
      "축구협회 회장 선거",
      "축구협회장",
      "홍명보",
      "회장 선거"
    ],
    "issueTags": [
      "coach-appointment",
      "election",
      "innovation-committee",
      "mcst-audit"
    ],
    "personTags": [
      "person_chung_mong_gyu",
      "person_hong_myung_bo",
      "person_park_ji_sung"
    ],
    "sourceType": "news",
    "isOfficial": false,
    "relevanceScore": 100,
    "labels": [
      "감사 키워드 포함",
      "인물 언급"
    ]
  },
  {
    "id": "item_14f515dab2cd3472",
    "type": "news",
    "title": "\"능력 없이 돈 받아\"…홍명보·정몽규 고발 시민단체, 14일 경찰 조사",
    "summary": "경찰이 정몽규 전 대한 축구협회 장 등이 홍명보 국가대표팀 감독의 선임 과정에 부당하게 개입했다는 의혹에... 서민위는 지난 2일 정 회장과 이임생 전 기술이사, 홍 감독을 강요·협박·업무방해·업무상 배임 혐의로...",
    "url": "https://www.mt.co.kr/society/2026/07/12/2026071213252825658",
    "originalUrl": "https://www.mt.co.kr/society/2026/07/12/2026071213252825658",
    "publisher": "mt.co.kr",
    "publishedAt": "2026-07-12T04:36:00.000Z",
    "collectedAt": "2026-07-12T04:59:19.492Z",
    "matchedKeywords": [
      "\"이임생\" 대한축구협회",
      "\"이임생\" 축구협회",
      "\"정몽규\" 대한축구협회",
      "\"정몽규\" 축구협회",
      "\"홍명보\" 대한축구협회",
      "\"홍명보\" 축구협회",
      "대표팀 감독",
      "대표팀 감독 선임",
      "대한축구협회",
      "대한축구협회장",
      "이임생",
      "전력강화위원회",
      "정몽규",
      "축구협회",
      "축구협회 감독 선임",
      "축구협회장",
      "홍명보"
    ],
    "issueTags": [
      "coach-appointment",
      "election"
    ],
    "personTags": [
      "person_chung_mong_gyu",
      "person_hong_myung_bo",
      "person_lee_im_saeng"
    ],
    "sourceType": "news",
    "isOfficial": false,
    "relevanceScore": 76,
    "labels": [
      "인물 언급"
    ]
  },
  {
    "id": "item_200f8c2f8aa3f6cb",
    "type": "news",
    "title": "손흥민 배경에 오타니 출전 발표라니…다저스, 한정판 SON 버블헤드 배포...",
    "summary": "앞서 국회 문화체육관광위원회는 축구 행정과 대표팀 감독 선임 과정을 둘러싼 의혹을 살펴보겠다며 손흥민을 참고인 명단에 포함했다. 하지만 시즌을 소화 중인 현역 선수에게 장거리 이동 부담까지 안기는 것이...",
    "url": "https://www.spotvnews.co.kr/news/articleView.html?idxno=827959",
    "originalUrl": "https://www.spotvnews.co.kr/news/articleView.html?idxno=827959",
    "publisher": "spotvnews.co.kr",
    "publishedAt": "2026-07-12T04:12:00.000Z",
    "collectedAt": "2026-07-12T04:59:19.492Z",
    "matchedKeywords": [
      "감독 선임",
      "대표팀 감독",
      "대표팀 감독 선임"
    ],
    "issueTags": [
      "coach-appointment"
    ],
    "personTags": [],
    "sourceType": "news",
    "isOfficial": false,
    "relevanceScore": 20,
    "labels": []
  },
  {
    "id": "item_823fd54f768cec7f",
    "type": "news",
    "title": "경찰, 홍명보·정몽규 수사 본격화…14일 고발인 조사",
    "summary": "경찰이 홍명보 전 축구 국가대표팀 감독과 정몽규 전 대한 축구협회 장 등을 둘러싼 대한 축구협회 관련 수사에 본격 착수했다. 경찰은 홍 전 감독 선임 과정에서 정 전 회장과 이임생 전 기술이사가 전력강화위원회를...",
    "url": "https://www.nocutnews.co.kr/news/6546836?utm_source=naver&utm_medium=article&utm_campaign=20260712010858",
    "originalUrl": "https://www.nocutnews.co.kr/news/6546836?utm_source=naver&utm_medium=article&utm_campaign=20260712010858",
    "publisher": "nocutnews.co.kr",
    "publishedAt": "2026-07-12T04:09:00.000Z",
    "collectedAt": "2026-07-12T04:59:19.492Z",
    "matchedKeywords": [
      "\"이임생\" 대한축구협회",
      "\"이임생\" 축구협회",
      "\"정몽규\" 대한축구협회",
      "\"정몽규\" 축구협회",
      "\"홍명보\" 대한축구협회",
      "\"홍명보\" 축구협회",
      "감독 선임",
      "대표팀 감독",
      "대표팀 감독 선임",
      "대한축구협회",
      "대한축구협회장",
      "이임생",
      "전력강화위원회",
      "정몽규",
      "축구협회",
      "축구협회 감독 선임",
      "축구협회장",
      "홍명보"
    ],
    "issueTags": [
      "coach-appointment",
      "election"
    ],
    "personTags": [
      "person_chung_mong_gyu",
      "person_hong_myung_bo",
      "person_lee_im_saeng"
    ],
    "sourceType": "news",
    "isOfficial": false,
    "relevanceScore": 100,
    "labels": [
      "인물 언급"
    ]
  },
  {
    "id": "item_3555dd525743ea16",
    "type": "news",
    "title": "한 주간의 이슈 검색어 Top10 [시선뉴스 키워드]",
    "summary": "정몽규 축구협회 장 사임 대한축구협회를 이끌어온 정몽규 회장이 최근 불거진 각종 논란에 책임을 지고 13년 5개월여 만에 수장직에서 전격 물러났다. 축구협회는 정 회장이 6일 오전 천안...",
    "url": "http://www.sisunnews.co.kr/news/articleView.html?idxno=242231",
    "originalUrl": "http://www.sisunnews.co.kr/news/articleView.html?idxno=242231",
    "publisher": "sisunnews.co.kr",
    "publishedAt": "2026-07-12T04:00:00.000Z",
    "collectedAt": "2026-07-12T04:59:19.492Z",
    "matchedKeywords": [
      "\"정몽규\" 대한축구협회",
      "\"정몽규\" 축구협회",
      "대한축구협회",
      "대한축구협회장",
      "정몽규",
      "축구 혁신",
      "축구혁신위",
      "축구협회",
      "축구협회 혁신위원회",
      "축구협회장",
      "혁신위원회",
      "K-축구혁신위원회"
    ],
    "issueTags": [
      "election",
      "innovation-committee"
    ],
    "personTags": [
      "person_chung_mong_gyu"
    ],
    "sourceType": "news",
    "isOfficial": false,
    "relevanceScore": 48,
    "labels": [
      "인물 언급"
    ]
  },
  {
    "id": "item_d2c23635e28f93bb",
    "type": "news",
    "title": "“세계적인 무대에서 뛰는 이강인 플레이에 감탄했다…축구 잘하면 형”...",
    "summary": "대표팀 경험이 거의 없었던 이기혁은 월드컵을 앞두고 전격 홍명보호 스리백의 핵심으로 발탁됐다.... 그만큼 이기혁은 홍명보 감독 에게 예쁨을 받았다. 이기혁은 9일 MBC, SBS와 인터뷰에 임해 월드컵 소감을 전했다....",
    "url": "http://www.osen.co.kr/article/G1112838185",
    "originalUrl": "http://www.osen.co.kr/article/G1112838185",
    "publisher": "osen.co.kr",
    "publishedAt": "2026-07-12T03:17:00.000Z",
    "collectedAt": "2026-07-12T04:59:19.492Z",
    "matchedKeywords": [
      "대표팀 감독",
      "홍명보"
    ],
    "issueTags": [],
    "personTags": [
      "person_hong_myung_bo"
    ],
    "sourceType": "news",
    "isOfficial": false,
    "relevanceScore": 8,
    "relevanceTier": "secondary",
    "labels": [
      "인물 언급"
    ]
  },
  {
    "id": "item_0f2719fea48d848c",
    "type": "news",
    "title": "“능력 안되는데 돈 받아”…홍명보 감독 고발한 시민단체, 14일 경찰 조...",
    "summary": "뉴스1 서민위는 앞선 2일 정몽규 대한 축구협회 장과 이임생 전 기술이사, 홍 감독을 강요, 협박, 업무방해, 업무상 배임 등 혐의로 고발한 바 있다. 서민위는 “정 회장과 이 전 이사가 홍 감독 선임 과정에서 전력강화위를...",
    "url": "https://www.segye.com/newsView/20260712506859?OutUrl=naver",
    "originalUrl": "https://www.segye.com/newsView/20260712506859?OutUrl=naver",
    "publisher": "segye.com",
    "publishedAt": "2026-07-12T03:15:00.000Z",
    "collectedAt": "2026-07-12T04:59:19.492Z",
    "matchedKeywords": [
      "\"이임생\" 대한축구협회",
      "\"이임생\" 축구협회",
      "\"정몽규\" 대한축구협회",
      "\"정몽규\" 축구협회",
      "\"홍명보\" 대한축구협회",
      "\"홍명보\" 축구협회",
      "감독 선임",
      "대표팀 감독",
      "대표팀 감독 선임",
      "대한축구협회",
      "대한축구협회장",
      "이임생",
      "전력강화위원회",
      "정몽규",
      "축구협회",
      "축구협회 감독 선임",
      "축구협회장",
      "홍명보"
    ],
    "issueTags": [
      "coach-appointment",
      "election"
    ],
    "personTags": [
      "person_chung_mong_gyu",
      "person_hong_myung_bo",
      "person_lee_im_saeng"
    ],
    "sourceType": "news",
    "isOfficial": false,
    "relevanceScore": 84,
    "labels": [
      "인물 언급"
    ]
  },
  {
    "id": "item_eb2e5b3c75e8a87a",
    "type": "news",
    "title": "[ET시선]정쟁에 멈춘 협치",
    "summary": "문체위는 대한축구협회 현안 청문회 실시 계획까지 처리했다. 상임위는 본래 법안과 정책을 놓고 여야가 토론하고 수정하며 합의를 모색하는 공간이다. 다양한 이해관계를 조정하고 입법 과정에서 부족한 부분을 보완하는...",
    "url": "https://www.etnews.com/20260710000098",
    "originalUrl": "https://www.etnews.com/20260710000098",
    "publisher": "etnews.com",
    "publishedAt": "2026-07-12T03:01:00.000Z",
    "collectedAt": "2026-07-12T04:59:19.492Z",
    "matchedKeywords": [
      "대한축구협회",
      "축구협회"
    ],
    "issueTags": [],
    "personTags": [],
    "sourceType": "news",
    "isOfficial": false,
    "relevanceScore": 30,
    "relevanceTier": "secondary",
    "labels": []
  },
  {
    "id": "item_431d517b3e6b1aac",
    "type": "news",
    "title": "'내가 홍명보호 전술 본체' 아로소 코치, '처참한 스리백' 남기고 한국 ...",
    "summary": "‘대한 축구협회 는 얼굴인 한국인 감독과 훈련과 경기 계획을 총괄하는 외국인 코치를 원했다’라며 사실상 스스로가 홍명보 호 전술의 핵심이라는 듯한 뉘앙스가 전해졌다. 물론 이는 오역으로 인한 오해였다. 아로소...",
    "url": "https://www.mydaily.co.kr/page/view/2026071211562758143",
    "originalUrl": "https://www.mydaily.co.kr/page/view/2026071211562758143",
    "publisher": "mydaily.co.kr",
    "publishedAt": "2026-07-12T02:57:00.000Z",
    "collectedAt": "2026-07-12T04:59:19.492Z",
    "matchedKeywords": [
      "\"홍명보\" 대한축구협회",
      "\"홍명보\" 축구협회",
      "대표팀 감독",
      "대한축구협회",
      "지도자",
      "축구협회",
      "축구협회 지도자",
      "홍명보"
    ],
    "issueTags": [
      "coach-appointment",
      "youth-governance"
    ],
    "personTags": [
      "person_hong_myung_bo"
    ],
    "sourceType": "news",
    "isOfficial": false,
    "relevanceScore": 38,
    "labels": [
      "인물 언급"
    ]
  },
  {
    "id": "item_70b204920f0bd437",
    "type": "news",
    "title": "경찰, 홍명보·정몽규 수사 본격화…14일 고발인 조사",
    "summary": "정몽규 전 대한 축구협회 장과 이임생 전 기술이사가 홍명보 국가대표팀 감독의 선임 과정에서 전력강화위원회를 협박했다며 추가 고발이 된 사건에 대해 경찰이 본격적으로 수사에 나선다. 12일 경찰에 따르면 서울경찰청...",
    "url": "https://www.news1.kr/society/incident-accident/6225288",
    "originalUrl": "https://www.news1.kr/society/incident-accident/6225288",
    "publisher": "news1.kr",
    "publishedAt": "2026-07-12T02:06:00.000Z",
    "collectedAt": "2026-07-12T04:59:19.492Z",
    "matchedKeywords": [
      "\"이임생\" 대한축구협회",
      "\"이임생\" 축구협회",
      "\"정몽규\" 대한축구협회",
      "\"정몽규\" 축구협회",
      "\"홍명보\" 대한축구협회",
      "\"홍명보\" 축구협회",
      "대표팀 감독",
      "대표팀 감독 선임",
      "대한축구협회",
      "대한축구협회장",
      "이임생",
      "전력강화위원회",
      "정몽규",
      "축구협회",
      "축구협회 감독 선임",
      "축구협회장",
      "홍명보"
    ],
    "issueTags": [
      "coach-appointment",
      "election"
    ],
    "personTags": [
      "person_chung_mong_gyu",
      "person_hong_myung_bo",
      "person_lee_im_saeng"
    ],
    "sourceType": "news",
    "isOfficial": false,
    "relevanceScore": 94,
    "labels": [
      "인물 언급"
    ]
  },
  {
    "id": "item_8685c716156e2c00",
    "type": "news",
    "title": "[여의도풍향계] \"책임 물어야\" vs \"망신주기\" 국회 출석 '잔혹사'",
    "summary": "회장, 이임생 전 기술총괄이사 등 증인 채택도 끝마쳤습니다. 월드컵 때 많은 사람들을 갸우뚱하게 만들었던... 이 일에 대해서 관심을 가져주셔서 너무 감사 드리고.\" 국감장에서, 직접 겪은 이른바 '사이버레커'들의...",
    "url": "http://www.yonhapnewstv.co.kr/news/MYH20260711152536bLU",
    "originalUrl": "http://www.yonhapnewstv.co.kr/news/MYH20260711152536bLU",
    "publisher": "yonhapnewstv.co.kr",
    "publishedAt": "2026-07-12T02:01:00.000Z",
    "collectedAt": "2026-07-12T04:59:19.492Z",
    "matchedKeywords": [
      "\"이임생\" 감사",
      "\"이임생\" 축구협회",
      "\"정몽규\" 감사",
      "\"정몽규\" 축구협회",
      "\"홍명보\" 감사",
      "\"홍명보\" 축구협회",
      "감독 선임",
      "감사",
      "대표팀 감독",
      "대표팀 감독 선임",
      "이임생",
      "정몽규",
      "축구협회",
      "축구협회 감독 선임",
      "축구협회 감사",
      "홍명보"
    ],
    "issueTags": [
      "coach-appointment",
      "mcst-audit"
    ],
    "personTags": [
      "person_chung_mong_gyu",
      "person_hong_myung_bo",
      "person_lee_im_saeng"
    ],
    "sourceType": "news",
    "isOfficial": false,
    "relevanceScore": 44,
    "labels": [
      "감사 키워드 포함",
      "인물 언급"
    ]
  },
  {
    "id": "item_28b2e71de9c70b4a",
    "type": "news",
    "title": "[북중미 월드컵] \"홍명보 감독님, 진심으로 감사합니다\" 페드로 로마 GK...",
    "summary": "2026 국제축구연맹(FIFA) 북중미 월드컵을 끝으로 대한민국 국가대표팀을 떠난 페드로 로마(55) 골키퍼 코치가 대한축구협회(KFA)와 홍명보 (57) 감독에게 감사 의 뜻을 전했다. 포르투갈 코임브라 지역지 '디아리오 드...",
    "url": "https://www.goal.com/kr/뉴스/a/blt774912854b1a7c69",
    "originalUrl": "https://www.goal.com/kr/뉴스/a/blt774912854b1a7c69",
    "publisher": "goal.com",
    "publishedAt": "2026-07-12T01:30:00.000Z",
    "collectedAt": "2026-07-12T04:59:19.492Z",
    "matchedKeywords": [
      "\"홍명보\" 감사",
      "\"홍명보\" 대한축구협회",
      "\"홍명보\" 축구협회",
      "감사",
      "대한축구협회",
      "축구협회",
      "축구협회 감사",
      "홍명보",
      "KFA"
    ],
    "issueTags": [
      "mcst-audit"
    ],
    "personTags": [
      "person_hong_myung_bo"
    ],
    "sourceType": "news",
    "isOfficial": false,
    "relevanceScore": 63,
    "labels": [
      "감사 키워드 포함",
      "인물 언급"
    ]
  },
  {
    "id": "item_78f5b42d3a75152b",
    "type": "news",
    "title": "\"패배한다는 것은…\" 말 잇지 못한 솔바켄 노르웨이 감독, 잉글랜드전 ...",
    "summary": "김태석 기자 스톨레 솔바켄 노르웨이 축구 국가 대표팀 감독 이 잉글랜드전에서 석패한 후 분루를 삼켰다. 결과를 가슴으로 쉽게 받아들이지 못하는 모습이다. 솔바켄 감독이 이끄는 노르웨이는 12일 오전 6시(한국 시각)...",
    "url": "https://www.besteleven.com/news/articleView.html?idxno=309831",
    "originalUrl": "https://www.besteleven.com/news/articleView.html?idxno=309831",
    "publisher": "besteleven.com",
    "publishedAt": "2026-07-12T01:11:00.000Z",
    "collectedAt": "2026-07-12T01:13:31.141Z",
    "matchedKeywords": [
      "대표팀 감독"
    ],
    "issueTags": [
      "coach-appointment"
    ],
    "personTags": [],
    "sourceType": "news",
    "isOfficial": false,
    "relevanceScore": 10,
    "relevanceTier": "secondary",
    "labels": []
  },
  {
    "id": "item_89d0c676e058bb0d",
    "type": "news",
    "title": "'연봉 26억→86억' 혹시... 역시... 크로아티아 황금기 이끈 달리치, 다...",
    "summary": "대한민국 축구대표팀 차기 사령탑 후보로도 거론됐던 즐라트코 달리치 전 크로아티아 대표팀 감독 이 결국 중동행을 선택할 것으로 보인다. 레바논 매체 '엘스포츠'는 10일(한국시간) \"즐라트코 달리치 감독이...",
    "url": "http://www.osen.co.kr/article/G1112838487",
    "originalUrl": "http://www.osen.co.kr/article/G1112838487",
    "publisher": "osen.co.kr",
    "publishedAt": "2026-07-12T01:06:00.000Z",
    "collectedAt": "2026-07-12T01:13:31.141Z",
    "matchedKeywords": [
      "대표팀 감독"
    ],
    "issueTags": [
      "coach-appointment"
    ],
    "personTags": [],
    "sourceType": "news",
    "isOfficial": false,
    "relevanceScore": 10,
    "relevanceTier": "secondary",
    "labels": []
  },
  {
    "id": "item_1a375f454bbac283",
    "type": "news",
    "title": "\"괴물을 왜 빼요!\" '충격' 벤치 OUT→눈물 감춘 '괴물 공격수' 엘링 홀란...",
    "summary": "스탈레 솔바켄 노르웨이 월드컵 대표팀 감독 이 이끄는 노르웨이는 12일 오전 6시(이하 한국시각) 미국의 마이애미 스타디움에서 잉글랜드와 2026년 북중미월드컵 8강전을 치렀다. 객관적 전력으로 놓고 보면 노르웨이가...",
    "url": "https://www.sportschosun.com/football/2026-07-12/202607120100074660004719",
    "originalUrl": "https://www.sportschosun.com/football/2026-07-12/202607120100074660004719",
    "publisher": "sportschosun.com",
    "publishedAt": "2026-07-12T01:06:00.000Z",
    "collectedAt": "2026-07-12T01:13:31.141Z",
    "matchedKeywords": [
      "대표팀 감독"
    ],
    "issueTags": [
      "coach-appointment"
    ],
    "personTags": [],
    "sourceType": "news",
    "isOfficial": false,
    "relevanceScore": 10,
    "relevanceTier": "secondary",
    "labels": []
  },
  {
    "id": "item_4aea42c4dc7f365c",
    "type": "news",
    "title": "깜짝 고백! 韓 차기 감독 거론 아기레, \"최종 결정은 그녀가 내릴 것\".....",
    "summary": "앞서 한국은 2026 국제 축구 연맹(FIFA) 북중미 월드컵서 32강 진출에 실패했다. 이에 홍명보 전 감독은 멕시코... 객관적으로, 이른 시일 내에 대한 축구협회 가 새로운 감독 선임을 위한 협상 테이블을 꾸릴 수 있을지조차...",
    "url": "https://www.sportalkorea.com/news/articleView.html?idxno=2025052909553369144",
    "originalUrl": "https://www.sportalkorea.com/news/articleView.html?idxno=2025052909553369144",
    "publisher": "sportalkorea.com",
    "publishedAt": "2026-07-12T00:51:00.000Z",
    "collectedAt": "2026-07-12T04:59:19.492Z",
    "matchedKeywords": [
      "\"정몽규\" 대한축구협회",
      "\"정몽규\" 축구협회",
      "\"홍명보\" 대한축구협회",
      "\"홍명보\" 축구협회",
      "감독 선임",
      "대표팀 감독 선임",
      "대한축구협회",
      "정몽규",
      "지도자",
      "축구협회",
      "축구협회 감독 선임",
      "축구협회 감독 후보",
      "축구협회 지도자",
      "홍명보"
    ],
    "issueTags": [
      "coach-appointment",
      "youth-governance"
    ],
    "personTags": [
      "person_chung_mong_gyu",
      "person_hong_myung_bo"
    ],
    "sourceType": "news",
    "isOfficial": false,
    "relevanceScore": 48,
    "labels": [
      "인물 언급"
    ]
  },
  {
    "id": "item_28837943d47abf2c",
    "type": "news",
    "title": "‘첫 월드컵’ 홀란, ‘5G 7골 대폭발→첫 8강행 영웅→아쉬운 마무리’",
    "summary": "토마스 투헬 잉글랜드 축구대표팀 감독 은 홀란을 어떻게 상대해야 하는지를 완벽하게 이해하고 이날... 또 홀란은 지난 6일 브라질과의 16강전에서 멀티골을 터뜨리며, ‘영원한 우승 후보 ’를 집으로 돌려보냈다....",
    "url": "https://sports.donga.com/sports/article/all/20260712/134280069/1",
    "originalUrl": "https://sports.donga.com/sports/article/all/20260712/134280069/1",
    "publisher": "sports.donga.com",
    "publishedAt": "2026-07-12T00:42:00.000Z",
    "collectedAt": "2026-07-12T04:59:19.492Z",
    "matchedKeywords": [
      "감독 후보",
      "대표팀 감독"
    ],
    "issueTags": [
      "coach-appointment"
    ],
    "personTags": [],
    "sourceType": "news",
    "isOfficial": false,
    "relevanceScore": 10,
    "relevanceTier": "secondary",
    "labels": []
  },
  {
    "id": "item_7f35fe7aacd2140d",
    "type": "news",
    "title": "홍명보호와 맞붙었던 25세 남아공 국가대표 별세... \"한국전이 생애 마...",
    "summary": "남아공프로 축구 선수 협회 는 \"애덤스는 월드컵에서 자긍심과 용기, 뛰어난 활약으로 국민들의 사랑을 받았다\"며 \"그의 죽음은 가족과 동료, 소속팀과 남아공 축구 계 전체에 헤아릴 수 없는 상실\"이라고 밝혔다. 대표팀...",
    "url": "https://www.insight.co.kr/news/562610",
    "originalUrl": "https://www.insight.co.kr/news/562610",
    "publisher": "insight.co.kr",
    "publishedAt": "2026-07-12T00:24:00.000Z",
    "collectedAt": "2026-07-12T04:59:19.492Z",
    "matchedKeywords": [
      "\"홍명보\" 축구협회",
      "홍명보"
    ],
    "issueTags": [],
    "personTags": [
      "person_hong_myung_bo"
    ],
    "sourceType": "news",
    "isOfficial": false,
    "relevanceScore": 8,
    "relevanceTier": "secondary",
    "labels": [
      "인물 언급"
    ]
  },
  {
    "id": "item_19f2a0d86aa7bd7f",
    "type": "news",
    "title": "\"한국전이 생애 마지막 경기였다\"…남아공 25세 미드필더 애덤스 숨진 ...",
    "summary": "결과적으로 지난달 26일 홍명보 전 감독 이 이끌던 한국 대표팀 과의 조별리그 최종전(3차전)이 그의 생애 마지막 경기가 되었다. 당시 애덤스는 남아공이 1-0으로 앞서던 후반 34분 교체 투입되어 그라운드를 누볐다. 이후...",
    "url": "http://www.fnnews.com/news/202607120904415384",
    "originalUrl": "http://www.fnnews.com/news/202607120904415384",
    "publisher": "fnnews.com",
    "publishedAt": "2026-07-12T00:10:00.000Z",
    "collectedAt": "2026-07-12T01:13:31.141Z",
    "matchedKeywords": [
      "대표팀 감독",
      "홍명보"
    ],
    "issueTags": [],
    "personTags": [
      "person_hong_myung_bo"
    ],
    "sourceType": "news",
    "isOfficial": false,
    "relevanceScore": 8,
    "relevanceTier": "secondary",
    "labels": [
      "인물 언급"
    ]
  },
  {
    "id": "item_d4c48e7af0eeeb79",
    "type": "news",
    "title": "[발행인 칼럼] 홍명보를 위한 변명",
    "summary": "그래서 이번 청문회가 홍명보 한 사람을 심판하는 자리가 아니라, 왜 한국 축구 는 같은 논란을 반복하는지 묻는 자리가 되었으면 한다. 감독 선임 시스템은 투명했는지, 협회 의 의사결정 구조는 합리적인지, 책임과 권한은...",
    "url": "http://kor.theasian.asia/archives/409538",
    "originalUrl": "http://kor.theasian.asia/archives/409538",
    "publisher": "kor.theasian.asia",
    "publishedAt": "2026-07-12T00:00:00.000Z",
    "collectedAt": "2026-07-12T04:59:19.492Z",
    "matchedKeywords": [
      "\"홍명보\" 대한축구협회",
      "\"홍명보\" 축구협회",
      "감독 선임",
      "대표팀 감독",
      "대표팀 감독 선임",
      "대한축구협회",
      "지도자",
      "축구협회",
      "축구협회 감독 선임",
      "축구협회 지도자",
      "홍명보"
    ],
    "issueTags": [
      "coach-appointment",
      "youth-governance"
    ],
    "personTags": [
      "person_hong_myung_bo"
    ],
    "sourceType": "news",
    "isOfficial": false,
    "relevanceScore": 58,
    "labels": [
      "인물 언급"
    ]
  }
]
