[
  {
    "id": "item_0a90c5ddb8bdded3",
    "type": "news",
    "title": "대한축구협회, '정몽규 중징계' 1심에 항소 결정",
    "summary": "이해관계자인 정몽규 회장 대신 이사회를 이끈 이용수 대한축구협회 부회장은 \"항소 결정에도 불구하고... 문체부는 지난 2024년 11월 대한축구협회에 대한 감사 결과를 발표하며 정몽규 회장 등 주요 인사들에게...",
    "url": "http://www.hansbiz.co.kr/news/articleView.html?idxno=837492",
    "originalUrl": "http://www.hansbiz.co.kr/news/articleView.html?idxno=837492",
    "publisher": "hansbiz.co.kr",
    "publishedAt": "2026-05-07T10:48:00.000Z",
    "collectedAt": "2026-07-08T23:40:59.802Z",
    "matchedKeywords": [
      "\"이용수\" 감사",
      "감사",
      "대한축구협회",
      "부회장",
      "이사회",
      "정몽규",
      "축구협회"
    ],
    "issueTags": [
      "kfa-executives",
      "mcst-audit"
    ],
    "personTags": [
      "person_chung_mong_gyu"
    ],
    "sourceType": "news",
    "isOfficial": false,
    "relevanceScore": 73,
    "labels": [
      "감사 키워드 포함",
      "인물 언급"
    ]
  },
  {
    "id": "item_c2f6119f748af1a9",
    "type": "news",
    "title": "\"춘천시, 강원FC 홈경기 유치 실패\" 정광열 측 공세...육동한 책임론 제...",
    "summary": "이에 대해 육동한 후보 측은 클린 선거 하겠다며 대응하지 않고 있다. 한편 강원FC 홈경기 춘천 미개최 문제는 지난해 김병지 대표이사의 춘천시 폄훼 논란과 시장 출입 금지 사태 등 일련의 갈등에서 비롯됐다. 당시...",
    "url": "http://www.fnnews.com/news/202605071621209027",
    "originalUrl": "http://www.fnnews.com/news/202605071621209027",
    "publisher": "fnnews.com",
    "publishedAt": "2026-05-07T07:56:00.000Z",
    "collectedAt": "2026-07-12T15:41:24.635Z",
    "matchedKeywords": [
      "\"김병지\" 선거",
      "김병지"
    ],
    "issueTags": [],
    "personTags": [
      "person_kim_byung_ji"
    ],
    "sourceType": "news",
    "isOfficial": false,
    "relevanceScore": 8,
    "relevanceTier": "secondary",
    "labels": [
      "인물 언급"
    ]
  },
  {
    "id": "item_945979eaf06b5f67",
    "type": "news",
    "title": "\"춘천시민에 강원FC 돌려줘야\" 정광열, 육동한 공세 …강원FC 갈등 재조...",
    "summary": "김병지 대표이사의 발언과 관련, 입장문을 통해 \"도민 화합을 위해 두 지자체를 균등하게 대해 왔다는 것을 설명하는 의미였고 강원FC는 구단을 사랑하고 지지해주시는 춘천시민을 포함한 모든 도민, 축구팬들에게 감사 ...",
    "url": "https://www.kado.net/news/articleView.html?idxno=2048793",
    "originalUrl": "https://www.kado.net/news/articleView.html?idxno=2048793",
    "publisher": "kado.net",
    "publishedAt": "2026-05-07T06:13:00.000Z",
    "collectedAt": "2026-07-12T15:41:24.635Z",
    "matchedKeywords": [
      "\"김병지\" 감사",
      "감사",
      "김병지"
    ],
    "issueTags": [
      "mcst-audit"
    ],
    "personTags": [
      "person_kim_byung_ji"
    ],
    "sourceType": "news",
    "isOfficial": false,
    "relevanceScore": 23,
    "labels": [
      "감사 키워드 포함",
      "인물 언급"
    ]
  }
]
